[
    {
        "id": 1,
        "name": "Mercedes Benz C Class Cabrio",
        "manufacturer": "Mercedes-Benz",
        "image": "car-1.jpg",
        "price": "$350",
        "description": "The Mercedes Benz C Class Cabrio combines elegant design with powerful performance. This cabriolet offers a luxurious open-top driving experience, making it perfect for sunny days.",
        "mileage": "57000",
        "transmission": "manual",
        "seats": "5 adults",
        "luggage": "4 bags",
        "fuel": "petrol",
        "features": [
            "AC",
            "Child seat",
            "GPS",
            "Luggage",
            "Music",
            "Seat belt",
            "Bluetooth",
            "Audio input",
            "Car kit",
            "Remote control locking",
            "Climate control"
        ]
    },
    {
        "id": 2,
        "name": "Range Rover Evoque",
        "manufacturer": "Range Rover",
        "image": "car-2.jpg",
        "price": "$200",
        "description": "The Range Rover Evoque is a stylish and versatile SUV. It offers a perfect blend of luxury and off-road capability, ensuring a comfortable and adventurous drive.",
        "mileage": "250000",
        "transmission": "manual",
        "seats": "5 adults",
        "luggage": "4 bags",
        "fuel": "diesel",
        "features": [
            "AC",
            "Child seat",
            "GPS",
            "Luggage",
            "Music",
            "Seat belt",
            "Bluetooth",
            "Audio input",
            "Car kit",
            "Remote control locking",
            "Climate control"
        ]
    },
    {
        "id": 3,
        "name": "Dodge Challenger",
        "manufacturer": "Dodge",
        "image": "car-4.jpg",
        "price": "$400",
        "description": "The Dodge Challenger is a classic American muscle car. Known for its bold design and powerful engine, it delivers an exhilarating driving experience.",
        "mileage": "20000",
        "transmission": "manual",
        "seats": "5 adults",
        "luggage": "4 bags",
        "fuel": "petrol",
        "features": [
            "AC",
            "Child seat",
            "GPS",
            "Luggage",
            "Music",
            "Seat belt",
            "Bluetooth",
            "Audio input",
            "Car kit",
            "Remote control locking",
            "Climate control"
        ]
    },
    {
        "id": 4,
        "name": "BMW X5",
        "manufacturer": "BMW",
        "image": "car-5.jpg",
        "price": "$350",
        "description": "The BMW X5 is a luxury SUV that offers a perfect blend of performance, comfort, and technology. It is ideal for families and long journeys.",
        "mileage": "300000",
        "transmission": "manual",
        "seats": "5 adults",
        "luggage": "4 bags",
        "fuel": "diesel",
        "features": [
            "AC",
            "Child seat",
            "GPS",
            "Luggage",
            "Music",
            "Seat belt",
            "Bluetooth",
            "Audio input",
            "Car kit",
            "Remote control locking",
            "Climate control"
        ]
    },
    {
        "id": 5,
        "name": "Alfa Romeo 4C",
        "manufacturer": "Alfa Romeo",
        "image": "car-6.jpg",
        "price": "$550",
        "description": "The Alfa Romeo 4C is a lightweight sports car known for its agility and stunning design. It offers an engaging driving experience with its sharp handling and responsive performance.",
        "mileage": "25000",
        "transmission": "manual",
        "seats": "5 adults",
        "luggage": "4 bags",
        "fuel": "petrol",
        "features": [
            "AC",
            "Child seat",
            "GPS",
            "Luggage",
            "Music",
            "Seat belt",
            "Bluetooth",
            "Audio input",
            "Car kit",
            "Remote control locking",
            "Climate control"
        ]
    },
    {
        "id": 6,
        "name": "Mercedes Benz E Class Cabrio",
        "manufacturer": "Mercedes-Benz",
        "image": "car-7.jpg",
        "price": "$350",
        "description": "The Mercedes Benz E Class Cabrio offers a luxurious open-top driving experience. With its elegant design and advanced features, it's perfect for both city drives and long trips.",
        "mileage": "170000",
        "transmission": "manual",
        "seats": "5 adults",
        "luggage": "4 bags",
        "fuel": "diesel",
        "features": [
            "AC",
            "Child seat",
            "GPS",
            "Luggage",
            "Music",
            "Seat belt",
            "Bluetooth",
            "Audio input",
            "Car kit",
            "Remote control locking",
            "Climate control"
        ]
    },
    {
        "id": 7,
        "name": "Jeep Wrangler Rubicon",
        "manufacturer": "Jeep",
        "image": "car-8.jpg",
        "price": "$300",
        "description": "The Jeep Wrangler Rubicon is an iconic off-road vehicle. It's built to handle rough terrains with ease, making it a great choice for adventure enthusiasts.",
        "mileage": "100000",
        "transmission": "manual",
        "seats": "5 adults",
        "luggage": "4 bags",
        "fuel": "diesel",
        "features": [
            "AC",
            "Child seat",
            "GPS",
            "Luggage",
            "Music",
            "Seat belt",
            "Bluetooth",
            "Audio input",
            "Car kit",
            "Remote control locking",
            "Climate control"
        ]
    },
    {
        "id": 8,
        "name": "VW Passat Alltrack",
        "manufacturer": "VW",
        "image": "passat.jpg",
        "price": "$999",
        "description": "The VW Passat Alltrack is a versatile and reliable estate car. It offers a spacious interior, advanced technology, and is perfect for long journeys and family trips.",
        "mileage": "255000",
        "transmission": "manual",
        "seats": "5 adults",
        "luggage": "4 bags",
        "fuel": "diesel",
        "features": [
            "AC",
            "Child seat",
            "GPS",
            "Luggage",
            "Music",
            "Seat belt",
            "Bluetooth",
            "Audio input",
            "Car kit",
            "Remote control locking",
            "Climate control"
        ]
    },
    {
        "id": 9,
        "name": "Mercedes Benz AMG GT",
        "manufacturer": "Mercedes-Benz",
        "image": "car-9.jpg",
        "price": "$550",
        "description": "The Mercedes Benz AMG GT is a high-performance sports car. With its sleek design and powerful engine, it offers an exhilarating driving experience.",
        "mileage": "40000",
        "transmission": "manual",
        "seats": "5 adults",
        "luggage": "4 bags",
        "fuel": "petrol",
        "features": [
            "AC",
            "Child seat",
            "GPS",
            "Luggage",
            "Music",
            "Seat belt",
            "Bluetooth",
            "Audio input",
            "Car kit",
            "Remote control locking",
            "Climate control"
        ]
    },
    {
        "id": 10,
        "name": "Mercedes Benz AMG GT S",
        "manufacturer": "Mercedes-Benz",
        "image": "car-10.jpg",
        "price": "$600",
        "description": "The Mercedes Benz AMG GT S is an advanced version of the AMG GT, offering even more power and luxury. It's designed for those who demand the best in performance and style.",
        "mileage": "35000",
        "transmission": "manual",
        "seats": "5 adults",
        "luggage": "4 bags",
        "fuel": "petrol",
        "features": [
            "AC",
            "Child seat",
            "GPS",
            "Luggage",
            "Music",
            "Seat belt",
            "Bluetooth",
            "Audio input",
            "Car kit",
            "Remote control locking",
            "Climate control"
        ]
    },
    {
        "id": 11,
        "name": "Mercedes Benz A Class",
        "manufacturer": "Mercedes-Benz",
        "image": "car-11.jpg",
        "price": "$170",
        "description": "The Mercedes Benz A Class is a compact car that combines luxury and practicality. It's ideal for city driving with its stylish design and efficient performance.",
        "mileage": "450000",
        "transmission": "manual",
        "seats": "5 adults",
        "luggage": "4 bags",
        "fuel": "diesel",
        "features": [
            "AC",
            "Child seat",
            "GPS",
            "Luggage",
            "Music",
            "Seat belt",
            "Bluetooth",
            "Audio input",
            "Car kit",
            "Remote control locking",
            "Climate control"
        ]
    },
    {
        "id": 12,
        "name": "Audi Q1",
        "manufacturer": "Audi",
        "image": "car-12.jpg",
        "price": "$220",
        "description": "The Audi Q1 is a compact SUV that offers a blend of luxury, performance, and practicality. It's perfect for urban driving as well as longer journeys.",
        "mileage": "210000",
        "transmission": "manual",
        "seats": "5 adults",
        "luggage": "4 bags",
        "fuel": "diesel",
        "features": [
            "AC",
            "Child seat",
            "GPS",
            "Luggage",
            "Music",
            "Seat belt",
            "Bluetooth",
            "Audio input",
            "Car kit",
            "Remote control locking",
            "Climate control"
        ]
    }
]
